roc/__init__.py
roc/idb/__init__.py
roc/idb/commands/__init__.py
roc/idb/commands/export.py
roc/idb/commands/list.py
roc/idb/commands/load.py
roc/idb/connector.py
roc/idb/constants.py
roc/idb/converters/__init__.py
roc/idb/converters/cdf_fill.py
roc/idb/converters/idb_to_bit.py
roc/idb/converters/idb_to_cdf.py
roc/idb/converters/idb_to_numpy.py
roc/idb/descriptor.json
roc/idb/exceptions.py
roc/idb/manager.py
roc/idb/models/__init__.py
roc/idb/models/idb.py
roc/idb/models/music/__init__.py
roc/idb/models/music/base.py
roc/idb/models/music/figaro.py
roc/idb/models/palisade_metadata.py
roc/idb/models/versions/README.rst
roc/idb/models/versions/roc_idb_0001_initial_.py
roc/idb/parsers/__init__.py
roc/idb/parsers/idb_elements.py
roc/idb/parsers/idb_parser.py
roc/idb/parsers/mib_parser/__init__.py
roc/idb/parsers/mib_parser/parse_sequence_mixin.py
roc/idb/parsers/mib_parser/procedure.py
roc/idb/parsers/palisade_parser/__init__.py
roc/idb/parsers/palisade_parser/base_palisade_parser.py
roc/idb/parsers/palisade_parser/enumeration_parser.py
roc/idb/parsers/palisade_parser/packet_parser.py
roc/idb/parsers/palisade_parser/palisade_metadata_parser.py
roc/idb/parsers/palisade_parser/palisade_parser.py
roc/idb/parsers/palisade_parser/parameter_parser.py
roc/idb/parsers/palisade_parser/tf_parser.py
roc/idb/parsers/srdb_parser/__init__.py
roc/idb/parsers/srdb_parser/dtypes.py
roc/idb/parsers/srdb_parser/srdb_parser.py
roc/idb/tasks/__init__.py
roc/idb/tasks/clear_release.py
roc/idb/tasks/export_sequences.py
roc/idb/tasks/install.py
roc/idb/tasks/list.py
roc/idb/tasks/load.py
roc/idb/tasks/load_idb_dump.py
roc/idb/tasks/load_palisade_metadata.py
roc/idb/tasks/load_sequences.py
roc/idb/tasks/parse_sequences.py
roc/idb/tasks/set_current.py
roc/idb/tasks/set_trange.py
roc/idb/tests/__init__.py
roc/idb/tests/idb_test_util.py
roc/idb/tests/test_clear_release.py
roc/idb/tests/test_install_load_idb.py
roc/idb/tests/test_load_idb_dump.py
roc/idb/tests/test_set_trange.py
roc_idb-1.5.2.dist-info/LICENSE
roc_idb-1.5.2.dist-info/METADATA
roc_idb-1.5.2.dist-info/WHEEL
roc_idb-1.5.2.dist-info/RECORD
