Metadata-Version: 2.3
Name: roc-idb
Version: 1.5.2
Summary: Plugin to manage the RPW Instrument Database (IDB)
Home-page: https://gitlab.obspm.fr/ROC/Pipelines/Plugins/IDB
License: CeCILL 2.1
Author: Xavier BONNIN
Author-email: xavier.bonnin@obspm.fr
Requires-Python: >=3.9,<4
Classifier: License :: Other/Proprietary License
Classifier: Programming Language :: Python :: 3
Classifier: Programming Language :: Python :: 3.9
Classifier: Programming Language :: Python :: 3.10
Classifier: Programming Language :: Python :: 3.11
Classifier: Programming Language :: Python :: 3.12
Classifier: Programming Language :: Python :: 3.13
Requires-Dist: numpy (>=1.20,<3)
Requires-Dist: poppy-core (>0.12.0)
Requires-Dist: poppy-pop (>0.12.0)
Requires-Dist: requests (>=2,<3)
Requires-Dist: sqlalchemy (>=2,<3)
Requires-Dist: xlwt (==1.3.0)
Project-URL: Repository, https://gitlab.obspm.fr/ROC/Pipelines/Plugins/IDB
